aurora_client/__init__.py
aurora_client/database.py
aurora_client/aurora/AuroraDB_pb2.py
aurora_client/aurora/AuroraDB_pb2_grpc.py
aurora_client/aurora/Aurora_pb2.py
aurora_client/aurora/Aurora_pb2_grpc.py
aurora_client/aurora/__init__.py
aurora_client-0.0.1.1.dist-info/LICENSE
aurora_client-0.0.1.1.dist-info/METADATA
aurora_client-0.0.1.1.dist-info/WHEEL
aurora_client-0.0.1.1.dist-info/top_level.txt
aurora_client-0.0.1.1.dist-info/RECORD
