Metadata-Version: 2.1
Name: aurora-client
Version: 0.0.1.1
Summary: aurora client
Home-page: https://gitlab.com/quintuple/aurora
Author: Jack Z.
Author-email: jDevlin685@outlook.com
License: UNKNOWN
Platform: UNKNOWN
Classifier: Programming Language :: Python :: 3
Classifier: License :: OSI Approved :: MIT License
Classifier: Operating System :: OS Independent
Requires-Python: >=3.6
